llama_index/readers/myscale/__init__.py
llama_index/readers/myscale/base.py
llama_index_readers_myscale-0.4.1.dist-info/METADATA
llama_index_readers_myscale-0.4.1.dist-info/WHEEL
llama_index_readers_myscale-0.4.1.dist-info/licenses/LICENSE
llama_index_readers_myscale-0.4.1.dist-info/RECORD
