Metadata-Version: 2.4
Name: llama-index-readers-myscale
Version: 0.4.1
Summary: llama-index readers myscale integration
Author-email: Your Name <you@example.com>
License-Expression: MIT
License-File: LICENSE
Requires-Python: <4.0,>=3.9
Requires-Dist: clickhouse-connect<0.8,>=0.7.0
Requires-Dist: llama-index-core<0.15,>=0.13.0
